investimentos/__init__.py
investimentos/investimentos.py
my_investimento-0.1.dist-info/licenses/LICENSE
my_investimento-0.1.dist-info/METADATA
my_investimento-0.1.dist-info/WHEEL
my_investimento-0.1.dist-info/top_level.txt
my_investimento-0.1.dist-info/RECORD
